payu/__init__.py
payu/admin.py
payu/conf.py
payu/forms.py
payu/models.py
payu/payments.py
payu/signals.py
payu/urls.py
payu/views.py
payu/management/__init__.py
payu/management/commands/__init__.py
payu/management/commands/send_idns.py
payu/migrations/0001_initial.py
payu/migrations/0002_payutoken_token_hash.py
payu/migrations/0003_auto_20200820_0858.py
payu/migrations/0004_auto_20210628_1208.py
payu/migrations/__init__.py
payu/templates/custom_hidden.html
tests/__init__.py
tests/conftest.py
tests/pytest_fixtures.py
tests/test_forms.py
tests/test_models.py
tests/test_payments.py
tests/test_send_idns_command.py
tests/test_views.py
django_payu_ro-1.6.0.dist-info/LICENSE
django_payu_ro-1.6.0.dist-info/METADATA
django_payu_ro-1.6.0.dist-info/WHEEL
django_payu_ro-1.6.0.dist-info/top_level.txt
django_payu_ro-1.6.0.dist-info/RECORD
